{
  "statistics": {
    "detectionDate": "2023-07-13T23:12:22.632Z",
    "formats": {
      "json": {
        "sources": {
          "./Modules/Sources/UI/Resources/Assets.xcassets/roles/sheriff.imageset/Contents.json": {
            "lines": 20,
            "tokens": 111,
            "sources": 1,
            "clones": 0,
            "duplicatedLines": 0,
            "duplicatedTokens": 0,
            "percentage": 0,
            "percentageTokens": 0,
            "newDuplicatedLines": 0,
            "newClones": 0
          },
          "./Modules/Sources/UI/Resources/Assets.xcassets/roles/renegade.imageset/Contents.json": {
            "lines": 20,
            "tokens": 111,
            "sources": 1,
            "clones": 0,
            "duplicatedLines": 0,
            "duplicatedTokens": 0,
            "percentage": 0,
            "percentageTokens": 0,
            "newDuplicatedLines": 0,
            "newClones": 0
          },
          "./Modules/Sources/UI/Resources/Assets.xcassets/roles/outlaw.imageset/Contents.json": {
            "lines": 20,
            "tokens": 111,
            "sources": 1,
            "clones": 0,
            "duplicatedLines": 0,
            "duplicatedTokens": 0,
            "percentage": 0,
            "percentageTokens": 0,
            "newDuplicatedLines": 0,
            "newClones": 0
          },
          "./Modules/Sources/UI/Resources/Assets.xcassets/roles/deputy.imageset/Contents.json": {
            "lines": 20,
            "tokens": 111,
            "sources": 1,
            "clones": 0,
            "duplicatedLines": 0,
            "duplicatedTokens": 0,
            "percentage": 0,
            "percentageTokens": 0,
            "newDuplicatedLines": 0,
            "newClones": 0
          },
          "./Modules/Sources/UI/Resources/Assets.xcassets/figures/willyTheKid.imageset/Contents.json": {
            "lines": 20,
            "tokens": 111,
            "sources": 1,
            "clones": 0,
            "duplicatedLines": 0,
            "duplicatedTokens": 0,
            "percentage": 0,
            "percentageTokens": 0,
            "newDuplicatedLines": 0,
            "newClones": 0
          },
          "./Modules/Sources/UI/Resources/Assets.xcassets/figures/vultureSam.imageset/Contents.json": {
            "lines": 20,
            "tokens": 111,
            "sources": 1,
            "clones": 0,
            "duplicatedLines": 0,
            "duplicatedTokens": 0,
            "percentage": 0,
            "percentageTokens": 0,
            "newDuplicatedLines": 0,
            "newClones": 0
          },
          "./Modules/Sources/UI/Resources/Assets.xcassets/figures/suzyLafayette.imageset/Contents.json": {
            "lines": 20,
            "tokens": 111,
            "sources": 1,
            "clones": 0,
            "duplicatedLines": 0,
            "duplicatedTokens": 0,
            "percentage": 0,
            "percentageTokens": 0,
            "newDuplicatedLines": 0,
            "newClones": 0
          },
          "./Modules/Sources/UI/Resources/Assets.xcassets/figures/slabTheKiller.imageset/Contents.json": {
            "lines": 20,
            "tokens": 111,
            "sources": 1,
            "clones": 0,
            "duplicatedLines": 0,
            "duplicatedTokens": 0,
            "percentage": 0,
            "percentageTokens": 0,
            "newDuplicatedLines": 0,
            "newClones": 0
          },
          "./Modules/Sources/UI/Resources/Assets.xcassets/figures/sidKetchum.imageset/Contents.json": {
            "lines": 20,
            "tokens": 111,
            "sources": 1,
            "clones": 0,
            "duplicatedLines": 0,
            "duplicatedTokens": 0,
            "percentage": 0,
            "percentageTokens": 0,
            "newDuplicatedLines": 0,
            "newClones": 0
          },
          "./Modules/Sources/UI/Resources/Assets.xcassets/figures/roseDoolan.imageset/Contents.json": {
            "lines": 20,
            "tokens": 111,
            "sources": 1,
            "clones": 0,
            "duplicatedLines": 0,
            "duplicatedTokens": 0,
            "percentage": 0,
            "percentageTokens": 0,
            "newDuplicatedLines": 0,
            "newClones": 0
          },
          "./Modules/Sources/UI/Resources/Assets.xcassets/figures/pedroRamirez.imageset/Contents.json": {
            "lines": 20,
            "tokens": 111,
            "sources": 1,
            "clones": 0,
            "duplicatedLines": 0,
            "duplicatedTokens": 0,
            "percentage": 0,
            "percentageTokens": 0,
            "newDuplicatedLines": 0,
            "newClones": 0
          },
          "./Modules/Sources/UI/Resources/Assets.xcassets/figures/paulRegret.imageset/Contents.json": {
            "lines": 20,
            "tokens": 111,
            "sources": 1,
            "clones": 0,
            "duplicatedLines": 0,
            "duplicatedTokens": 0,
            "percentage": 0,
            "percentageTokens": 0,
            "newDuplicatedLines": 0,
            "newClones": 0
          },
          "./Modules/Sources/UI/Resources/Assets.xcassets/figures/luckyDuke.imageset/Contents.json": {
            "lines": 20,
            "tokens": 111,
            "sources": 1,
            "clones": 0,
            "duplicatedLines": 0,
            "duplicatedTokens": 0,
            "percentage": 0,
            "percentageTokens": 0,
            "newDuplicatedLines": 0,
            "newClones": 0
          },
          "./Modules/Sources/UI/Resources/Assets.xcassets/figures/kitCarlson.imageset/Contents.json": {
            "lines": 20,
            "tokens": 111,
            "sources": 1,
            "clones": 0,
            "duplicatedLines": 0,
            "duplicatedTokens": 0,
            "percentage": 0,
            "percentageTokens": 0,
            "newDuplicatedLines": 0,
            "newClones": 0
          },
          "./Modules/Sources/UI/Resources/Assets.xcassets/figures/jourdonnais.imageset/Contents.json": {
            "lines": 20,
            "tokens": 111,
            "sources": 1,
            "clones": 0,
            "duplicatedLines": 0,
            "duplicatedTokens": 0,
            "percentage": 0,
            "percentageTokens": 0,
            "newDuplicatedLines": 0,
            "newClones": 0
          },
          "./Modules/Sources/UI/Resources/Assets.xcassets/figures/jesseJones.imageset/Contents.json": {
            "lines": 20,
            "tokens": 111,
            "sources": 1,
            "clones": 0,
            "duplicatedLines": 0,
            "duplicatedTokens": 0,
            "percentage": 0,
            "percentageTokens": 0,
            "newDuplicatedLines": 0,
            "newClones": 0
          },
          "./Modules/Sources/UI/Resources/Assets.xcassets/figures/elGringo.imageset/Contents.json": {
            "lines": 20,
            "tokens": 111,
            "sources": 1,
            "clones": 0,
            "duplicatedLines": 0,
            "duplicatedTokens": 0,
            "percentage": 0,
            "percentageTokens": 0,
            "newDuplicatedLines": 0,
            "newClones": 0
          },
          "./Modules/Sources/UI/Resources/Assets.xcassets/figures/calamityJanet.imageset/Contents.json": {
            "lines": 20,
            "tokens": 111,
            "sources": 1,
            "clones": 0,
            "duplicatedLines": 0,
            "duplicatedTokens": 0,
            "percentage": 0,
            "percentageTokens": 0,
            "newDuplicatedLines": 0,
            "newClones": 0
          },
          "./Modules/Sources/UI/Resources/Assets.xcassets/figures/blackJack.imageset/Contents.json": {
            "lines": 20,
            "tokens": 111,
            "sources": 1,
            "clones": 0,
            "duplicatedLines": 0,
            "duplicatedTokens": 0,
            "percentage": 0,
            "percentageTokens": 0,
            "newDuplicatedLines": 0,
            "newClones": 0
          },
          "./Modules/Sources/UI/Resources/Assets.xcassets/figures/bartCassidy.imageset/Contents.json": {
            "lines": 20,
            "tokens": 111,
            "sources": 1,
            "clones": 0,
            "duplicatedLines": 0,
            "duplicatedTokens": 0,
            "percentage": 0,
            "percentageTokens": 0,
            "newDuplicatedLines": 0,
            "newClones": 0
          },
          "./Modules/Sources/UI/Resources/Assets.xcassets/cards/winchester.imageset/Contents.json": {
            "lines": 20,
            "tokens": 111,
            "sources": 1,
            "clones": 0,
            "duplicatedLines": 0,
            "duplicatedTokens": 0,
            "percentage": 0,
            "percentageTokens": 0,
            "newDuplicatedLines": 0,
            "newClones": 0
          },
          "./Modules/Sources/UI/Resources/Assets.xcassets/cards/wellsFargo.imageset/Contents.json": {
            "lines": 20,
            "tokens": 111,
            "sources": 1,
            "clones": 0,
            "duplicatedLines": 0,
            "duplicatedTokens": 0,
            "percentage": 0,
            "percentageTokens": 0,
            "newDuplicatedLines": 0,
            "newClones": 0
          },
          "./Modules/Sources/UI/Resources/Assets.xcassets/cards/volcanic.imageset/Contents.json": {
            "lines": 20,
            "tokens": 111,
            "sources": 1,
            "clones": 0,
            "duplicatedLines": 0,
            "duplicatedTokens": 0,
            "percentage": 0,
            "percentageTokens": 0,
            "newDuplicatedLines": 0,
            "newClones": 0
          },
          "./Modules/Sources/UI/Resources/Assets.xcassets/cards/stagecoach.imageset/Contents.json": {
            "lines": 20,
            "tokens": 111,
            "sources": 1,
            "clones": 0,
            "duplicatedLines": 0,
            "duplicatedTokens": 0,
            "percentage": 0,
            "percentageTokens": 0,
            "newDuplicatedLines": 0,
            "newClones": 0
          },
          "./Modules/Sources/UI/Resources/Assets.xcassets/cards/scope.imageset/Contents.json": {
            "lines": 20,
            "tokens": 111,
            "sources": 1,
            "clones": 0,
            "duplicatedLines": 0,
            "duplicatedTokens": 0,
            "percentage": 0,
            "percentageTokens": 0,
            "newDuplicatedLines": 0,
            "newClones": 0
          },
          "./Modules/Sources/UI/Resources/Assets.xcassets/cards/schofield.imageset/Contents.json": {
            "lines": 20,
            "tokens": 111,
            "sources": 1,
            "clones": 0,
            "duplicatedLines": 0,
            "duplicatedTokens": 0,
            "percentage": 0,
            "percentageTokens": 0,
            "newDuplicatedLines": 0,
            "newClones": 0
          },
          "./Modules/Sources/UI/Resources/Assets.xcassets/cards/saloon.imageset/Contents.json": {
            "lines": 20,
            "tokens": 111,
            "sources": 1,
            "clones": 0,
            "duplicatedLines": 0,
            "duplicatedTokens": 0,
            "percentage": 0,
            "percentageTokens": 0,
            "newDuplicatedLines": 0,
            "newClones": 0
          },
          "./Modules/Sources/UI/Resources/Assets.xcassets/cards/revCarabine.imageset/Contents.json": {
            "lines": 20,
            "tokens": 111,
            "sources": 1,
            "clones": 0,
            "duplicatedLines": 0,
            "duplicatedTokens": 0,
            "percentage": 0,
            "percentageTokens": 0,
            "newDuplicatedLines": 0,
            "newClones": 0
          },
          "./Modules/Sources/UI/Resources/Assets.xcassets/cards/remington.imageset/Contents.json": {
            "lines": 20,
            "tokens": 111,
            "sources": 1,
            "clones": 0,
            "duplicatedLines": 0,
            "duplicatedTokens": 0,
            "percentage": 0,
            "percentageTokens": 0,
            "newDuplicatedLines": 0,
            "newClones": 0
          },
          "./Modules/Sources/UI/Resources/Assets.xcassets/cards/panic.imageset/Contents.json": {
            "lines": 20,
            "tokens": 111,
            "sources": 1,
            "clones": 0,
            "duplicatedLines": 0,
            "duplicatedTokens": 0,
            "percentage": 0,
            "percentageTokens": 0,
            "newDuplicatedLines": 0,
            "newClones": 0
          },
          "./Modules/Sources/UI/Resources/Assets.xcassets/cards/mustang.imageset/Contents.json": {
            "lines": 20,
            "tokens": 111,
            "sources": 1,
            "clones": 0,
            "duplicatedLines": 0,
            "duplicatedTokens": 0,
            "percentage": 0,
            "percentageTokens": 0,
            "newDuplicatedLines": 0,
            "newClones": 0
          },
          "./Modules/Sources/UI/Resources/Assets.xcassets/cards/missed.imageset/Contents.json": {
            "lines": 20,
            "tokens": 111,
            "sources": 1,
            "clones": 0,
            "duplicatedLines": 0,
            "duplicatedTokens": 0,
            "percentage": 0,
            "percentageTokens": 0,
            "newDuplicatedLines": 0,
            "newClones": 0
          },
          "./Modules/Sources/UI/Resources/Assets.xcassets/cards/jail.imageset/Contents.json": {
            "lines": 20,
            "tokens": 111,
            "sources": 1,
            "clones": 0,
            "duplicatedLines": 0,
            "duplicatedTokens": 0,
            "percentage": 0,
            "percentageTokens": 0,
            "newDuplicatedLines": 0,
            "newClones": 0
          },
          "./Modules/Sources/UI/Resources/Assets.xcassets/cards/indians.imageset/Contents.json": {
            "lines": 20,
            "tokens": 111,
            "sources": 1,
            "clones": 0,
            "duplicatedLines": 0,
            "duplicatedTokens": 0,
            "percentage": 0,
            "percentageTokens": 0,
            "newDuplicatedLines": 0,
            "newClones": 0
          },
          "./Modules/Sources/UI/Resources/Assets.xcassets/cards/generalstore.imageset/Contents.json": {
            "lines": 20,
            "tokens": 111,
            "sources": 1,
            "clones": 0,
            "duplicatedLines": 0,
            "duplicatedTokens": 0,
            "percentage": 0,
            "percentageTokens": 0,
            "newDuplicatedLines": 0,
            "newClones": 0
          },
          "./Modules/Sources/UI/Resources/Assets.xcassets/cards/gatling.imageset/Contents.json": {
            "lines": 20,
            "tokens": 111,
            "sources": 1,
            "clones": 0,
            "duplicatedLines": 0,
            "duplicatedTokens": 0,
            "percentage": 0,
            "percentageTokens": 0,
            "newDuplicatedLines": 0,
            "newClones": 0
          },
          "./Modules/Sources/UI/Resources/Assets.xcassets/cards/dynamite.imageset/Contents.json": {
            "lines": 20,
            "tokens": 111,
            "sources": 1,
            "clones": 0,
            "duplicatedLines": 0,
            "duplicatedTokens": 0,
            "percentage": 0,
            "percentageTokens": 0,
            "newDuplicatedLines": 0,
            "newClones": 0
          },
          "./Modules/Sources/UI/Resources/Assets.xcassets/cards/duel.imageset/Contents.json": {
            "lines": 20,
            "tokens": 111,
            "sources": 1,
            "clones": 0,
            "duplicatedLines": 0,
            "duplicatedTokens": 0,
            "percentage": 0,
            "percentageTokens": 0,
            "newDuplicatedLines": 0,
            "newClones": 0
          },
          "./Modules/Sources/UI/Resources/Assets.xcassets/cards/catBalou.imageset/Contents.json": {
            "lines": 20,
            "tokens": 111,
            "sources": 1,
            "clones": 0,
            "duplicatedLines": 0,
            "duplicatedTokens": 0,
            "percentage": 0,
            "percentageTokens": 0,
            "newDuplicatedLines": 0,
            "newClones": 0
          },
          "./Modules/Sources/UI/Resources/Assets.xcassets/cards/beer.imageset/Contents.json": {
            "lines": 20,
            "tokens": 111,
            "sources": 1,
            "clones": 0,
            "duplicatedLines": 0,
            "duplicatedTokens": 0,
            "percentage": 0,
            "percentageTokens": 0,
            "newDuplicatedLines": 0,
            "newClones": 0
          },
          "./Modules/Sources/UI/Resources/Assets.xcassets/cards/barrel.imageset/Contents.json": {
            "lines": 20,
            "tokens": 111,
            "sources": 1,
            "clones": 0,
            "duplicatedLines": 0,
            "duplicatedTokens": 0,
            "percentage": 0,
            "percentageTokens": 0,
            "newDuplicatedLines": 0,
            "newClones": 0
          },
          "./Modules/Sources/UI/Resources/Assets.xcassets/cards/bang.imageset/Contents.json": {
            "lines": 20,
            "tokens": 111,
            "sources": 1,
            "clones": 0,
            "duplicatedLines": 0,
            "duplicatedTokens": 0,
            "percentage": 0,
            "percentageTokens": 0,
            "newDuplicatedLines": 0,
            "newClones": 0
          },
          "./Modules/Sources/UI/Resources/Assets.xcassets/turtlerock.imageset/Contents.json": {
            "lines": 20,
            "tokens": 111,
            "sources": 1,
            "clones": 0,
            "duplicatedLines": 0,
            "duplicatedTokens": 0,
            "percentage": 0,
            "percentageTokens": 0,
            "newDuplicatedLines": 0,
            "newClones": 0
          },
          "./Modules/Sources/UI/Resources/Assets.xcassets/roles/Contents.json": {
            "lines": 5,
            "tokens": 27,
            "sources": 1,
            "clones": 0,
            "duplicatedLines": 0,
            "duplicatedTokens": 0,
            "percentage": 0,
            "percentageTokens": 0,
            "newDuplicatedLines": 0,
            "newClones": 0
          },
          "./Modules/Sources/UI/Resources/Assets.xcassets/figures/Contents.json": {
            "lines": 5,
            "tokens": 27,
            "sources": 1,
            "clones": 0,
            "duplicatedLines": 0,
            "duplicatedTokens": 0,
            "percentage": 0,
            "percentageTokens": 0,
            "newDuplicatedLines": 0,
            "newClones": 0
          },
          "./Modules/Sources/UI/Resources/Assets.xcassets/cards/Contents.json": {
            "lines": 5,
            "tokens": 27,
            "sources": 1,
            "clones": 0,
            "duplicatedLines": 0,
            "duplicatedTokens": 0,
            "percentage": 0,
            "percentageTokens": 0,
            "newDuplicatedLines": 0,
            "newClones": 0
          },
          "./Modules/Sources/UI/Resources/Assets.xcassets/card_back.imageset/Contents.json": {
            "lines": 20,
            "tokens": 111,
            "sources": 1,
            "clones": 0,
            "duplicatedLines": 0,
            "duplicatedTokens": 0,
            "percentage": 0,
            "percentageTokens": 0,
            "newDuplicatedLines": 0,
            "newClones": 0
          },
          "./Modules/Sources/UI/Resources/Assets.xcassets/Contents.json": {
            "lines": 5,
            "tokens": 27,
            "sources": 1,
            "clones": 0,
            "duplicatedLines": 0,
            "duplicatedTokens": 0,
            "percentage": 0,
            "percentageTokens": 0,
            "newDuplicatedLines": 0,
            "newClones": 0
          }
        },
        "total": {
          "lines": 900,
          "tokens": 4992,
          "sources": 48,
          "clones": 0,
          "duplicatedLines": 0,
          "duplicatedTokens": 0,
          "percentage": 0,
          "percentageTokens": 0,
          "newDuplicatedLines": 0,
          "newClones": 0
        }
      },
      "swift": {
        "sources": {
          "./Modules/Sources/Game/Public/DSL/Modifiers/Player+Modifiers.swift": {
            "lines": 41,
            "tokens": 345,
            "sources": 1,
            "clones": 1,
            "duplicatedLines": 11,
            "duplicatedTokens": 99,
            "percentage": 26.83,
            "percentageTokens": 28.7,
            "newDuplicatedLines": 0,
            "newClones": 0
          },
          "./Modules/Sources/Game/Public/DSL/Modifiers/GameState+Modifiers.swift": {
            "lines": 52,
            "tokens": 514,
            "sources": 1,
            "clones": 1,
            "duplicatedLines": 11,
            "duplicatedTokens": 99,
            "percentage": 21.15,
            "percentageTokens": 19.26,
            "newDuplicatedLines": 0,
            "newClones": 0
          },
          "./Modules/Sources/Game/Public/DSL/Modifiers/GameAction+Modifiers.swift": {
            "lines": 23,
            "tokens": 120,
            "sources": 1,
            "clones": 0,
            "duplicatedLines": 0,
            "duplicatedTokens": 0,
            "percentage": 0,
            "percentageTokens": 0,
            "newDuplicatedLines": 0,
            "newClones": 0
          },
          "./Modules/Sources/Game/Public/DSL/Modifiers/CardStack+Modifiers.swift": {
            "lines": 12,
            "tokens": 65,
            "sources": 1,
            "clones": 0,
            "duplicatedLines": 0,
            "duplicatedTokens": 0,
            "percentage": 0,
            "percentageTokens": 0,
            "newDuplicatedLines": 0,
            "newClones": 0
          },
          "./Modules/Sources/Game/Public/DSL/Modifiers/CardLocation+Modifiers.swift": {
            "lines": 17,
            "tokens": 118,
            "sources": 1,
            "clones": 0,
            "duplicatedLines": 0,
            "duplicatedTokens": 0,
            "percentage": 0,
            "percentageTokens": 0,
            "newDuplicatedLines": 0,
            "newClones": 0
          },
          "./Modules/Sources/Game/Public/DSL/Modifiers/CardEffect+Modifiers.swift": {
            "lines": 41,
            "tokens": 380,
            "sources": 1,
            "clones": 0,
            "duplicatedLines": 0,
            "duplicatedTokens": 0,
            "percentage": 0,
            "percentageTokens": 0,
            "newDuplicatedLines": 0,
            "newClones": 0
          },
          "./Modules/Sources/Game/Public/DSL/Modifiers/Card+Modifiers.swift": {
            "lines": 20,
            "tokens": 116,
            "sources": 1,
            "clones": 0,
            "duplicatedLines": 0,
            "duplicatedTokens": 0,
            "percentage": 0,
            "percentageTokens": 0,
            "newDuplicatedLines": 0,
            "newClones": 0
          },
          "./Modules/Sources/Game/Public/DSL/Builders/StringBuilder.swift": {
            "lines": 17,
            "tokens": 90,
            "sources": 1,
            "clones": 0,
            "duplicatedLines": 0,
            "duplicatedTokens": 0,
            "percentage": 0,
            "percentageTokens": 0,
            "newDuplicatedLines": 0,
            "newClones": 0
          },
          "./Modules/Sources/Game/Public/DSL/Builders/PlayerAttributeBuilder.swift": {
            "lines": 13,
            "tokens": 59,
            "sources": 1,
            "clones": 0,
            "duplicatedLines": 0,
            "duplicatedTokens": 0,
            "percentage": 0,
            "percentageTokens": 0,
            "newDuplicatedLines": 0,
            "newClones": 0
          },
          "./Modules/Sources/Game/Public/DSL/Builders/PlayReqBuilder.swift": {
            "lines": 15,
            "tokens": 64,
            "sources": 1,
            "clones": 0,
            "duplicatedLines": 0,
            "duplicatedTokens": 0,
            "percentage": 0,
            "percentageTokens": 0,
            "newDuplicatedLines": 0,
            "newClones": 0
          },
          "./Modules/Sources/Game/Public/DSL/Builders/GameAttributeBuilder.swift": {
            "lines": 15,
            "tokens": 64,
            "sources": 1,
            "clones": 0,
            "duplicatedLines": 0,
            "duplicatedTokens": 0,
            "percentage": 0,
            "percentageTokens": 0,
            "newDuplicatedLines": 0,
            "newClones": 0
          },
          "./Modules/Sources/Game/Public/DSL/Builders/GameActionBuilder.swift": {
            "lines": 13,
            "tokens": 59,
            "sources": 1,
            "clones": 0,
            "duplicatedLines": 0,
            "duplicatedTokens": 0,
            "percentage": 0,
            "percentageTokens": 0,
            "newDuplicatedLines": 0,
            "newClones": 0
          },
          "./Modules/Sources/Game/Public/DSL/Builders/CardEffectBuilder.swift": {
            "lines": 21,
            "tokens": 103,
            "sources": 1,
            "clones": 0,
            "duplicatedLines": 0,
            "duplicatedTokens": 0,
            "percentage": 0,
            "percentageTokens": 0,
            "newDuplicatedLines": 0,
            "newClones": 0
          },
          "./Modules/Sources/Game/Public/DSL/Builders/CardBuilder.swift": {
            "lines": 17,
            "tokens": 90,
            "sources": 1,
            "clones": 0,
            "duplicatedLines": 0,
            "duplicatedTokens": 0,
            "percentage": 0,
            "percentageTokens": 0,
            "newDuplicatedLines": 0,
            "newClones": 0
          },
          "./Modules/Sources/Game/Public/DSL/Builders/CardActionBuilder.swift": {
            "lines": 15,
            "tokens": 64,
            "sources": 1,
            "clones": 0,
            "duplicatedLines": 0,
            "duplicatedTokens": 0,
            "percentage": 0,
            "percentageTokens": 0,
            "newDuplicatedLines": 0,
            "newClones": 0
          },
          "./Modules/Sources/Game/Public/DSL/Attributes/PlayerAttribute.swift": {
            "lines": 10,
            "tokens": 36,
            "sources": 1,
            "clones": 0,
            "duplicatedLines": 0,
            "duplicatedTokens": 0,
            "percentage": 0,
            "percentageTokens": 0,
            "newDuplicatedLines": 0,
            "newClones": 0
          },
          "./Modules/Sources/Game/Public/DSL/Attributes/Player+GameAttribute.swift": {
            "lines": 13,
            "tokens": 74,
            "sources": 1,
            "clones": 0,
            "duplicatedLines": 0,
            "duplicatedTokens": 0,
            "percentage": 0,
            "percentageTokens": 0,
            "newDuplicatedLines": 0,
            "newClones": 0
          },
          "./Modules/Sources/Game/Public/DSL/Attributes/InPlay.swift": {
            "lines": 17,
            "tokens": 110,
            "sources": 1,
            "clones": 0,
            "duplicatedLines": 0,
            "duplicatedTokens": 0,
            "percentage": 0,
            "percentageTokens": 0,
            "newDuplicatedLines": 0,
            "newClones": 0
          },
          "./Modules/Sources/Game/Public/DSL/Attributes/Hand.swift": {
            "lines": 17,
            "tokens": 110,
            "sources": 1,
            "clones": 0,
            "duplicatedLines": 0,
            "duplicatedTokens": 0,
            "percentage": 0,
            "percentageTokens": 0,
            "newDuplicatedLines": 0,
            "newClones": 0
          },
          "./Modules/Sources/Game/Public/DSL/Attributes/GameAttribute.swift": {
            "lines": 10,
            "tokens": 36,
            "sources": 1,
            "clones": 0,
            "duplicatedLines": 0,
            "duplicatedTokens": 0,
            "percentage": 0,
            "percentageTokens": 0,
            "newDuplicatedLines": 0,
            "newClones": 0
          },
          "./Modules/Sources/Game/Public/DSL/Attributes/DiscardPile.swift": {
            "lines": 17,
            "tokens": 108,
            "sources": 1,
            "clones": 0,
            "duplicatedLines": 0,
            "duplicatedTokens": 0,
            "percentage": 0,
            "percentageTokens": 0,
            "newDuplicatedLines": 0,
            "newClones": 0
          },
          "./Modules/Sources/Game/Public/DSL/Attributes/Deck.swift": {
            "lines": 17,
            "tokens": 108,
            "sources": 1,
            "clones": 0,
            "duplicatedLines": 0,
            "duplicatedTokens": 0,
            "percentage": 0,
            "percentageTokens": 0,
            "newDuplicatedLines": 0,
            "newClones": 0
          },
          "./Modules/Sources/Game/Public/DSL/Attributes/CardAction.swift": {
            "lines": 18,
            "tokens": 68,
            "sources": 1,
            "clones": 0,
            "duplicatedLines": 0,
            "duplicatedTokens": 0,
            "percentage": 0,
            "percentageTokens": 0,
            "newDuplicatedLines": 0,
            "newClones": 0
          },
          "./Modules/Sources/Game/Public/DSL/Attributes/Arena.swift": {
            "lines": 17,
            "tokens": 110,
            "sources": 1,
            "clones": 0,
            "duplicatedLines": 0,
            "duplicatedTokens": 0,
            "percentage": 0,
            "percentageTokens": 0,
            "newDuplicatedLines": 0,
            "newClones": 0
          },
          "./Modules/Sources/Game/Public/DSL/Attributes/Abilities.swift": {
            "lines": 17,
            "tokens": 106,
            "sources": 1,
            "clones": 0,
            "duplicatedLines": 0,
            "duplicatedTokens": 0,
            "percentage": 0,
            "percentageTokens": 0,
            "newDuplicatedLines": 0,
            "newClones": 0
          },
          "./Modules/Sources/Game/_Internal/Utils/String+ExtractCardName.swift": {
            "lines": 13,
            "tokens": 63,
            "sources": 1,
            "clones": 0,
            "duplicatedLines": 0,
            "duplicatedTokens": 0,
            "percentage": 0,
            "percentageTokens": 0,
            "newDuplicatedLines": 0,
            "newClones": 0
          },
          "./Modules/Sources/Game/_Internal/Utils/EffectContext+Extensions.swift": {
            "lines": 19,
            "tokens": 124,
            "sources": 1,
            "clones": 0,
            "duplicatedLines": 0,
            "duplicatedTokens": 0,
            "percentage": 0,
            "percentageTokens": 0,
            "newDuplicatedLines": 0,
            "newClones": 0
          },
          "./Modules/Sources/Game/_Internal/Utils/Array+Extensions.swift": {
            "lines": 28,
            "tokens": 196,
            "sources": 1,
            "clones": 0,
            "duplicatedLines": 0,
            "duplicatedTokens": 0,
            "percentage": 0,
            "percentageTokens": 0,
            "newDuplicatedLines": 0,
            "newClones": 0
          },
          "./Modules/Sources/Game/_Internal/Updating/Player+Updating.swift": {
            "lines": 42,
            "tokens": 304,
            "sources": 1,
            "clones": 0,
            "duplicatedLines": 0,
            "duplicatedTokens": 0,
            "percentage": 0,
            "percentageTokens": 0,
            "newDuplicatedLines": 0,
            "newClones": 0
          },
          "./Modules/Sources/Game/_Internal/Updating/GameState+Updating.swift": {
            "lines": 55,
            "tokens": 516,
            "sources": 1,
            "clones": 0,
            "duplicatedLines": 0,
            "duplicatedTokens": 0,
            "percentage": 0,
            "percentageTokens": 0,
            "newDuplicatedLines": 0,
            "newClones": 0
          },
          "./Modules/Sources/Game/_Internal/Updating/CardStack+Updating.swift": {
            "lines": 16,
            "tokens": 81,
            "sources": 1,
            "clones": 0,
            "duplicatedLines": 0,
            "duplicatedTokens": 0,
            "percentage": 0,
            "percentageTokens": 0,
            "newDuplicatedLines": 0,
            "newClones": 0
          },
          "./Modules/Sources/Game/_Internal/Updating/CardLocation+Updating.swift": {
            "lines": 24,
            "tokens": 173,
            "sources": 1,
            "clones": 0,
            "duplicatedLines": 0,
            "duplicatedTokens": 0,
            "percentage": 0,
            "percentageTokens": 0,
            "newDuplicatedLines": 0,
            "newClones": 0
          },
          "./Modules/Sources/Game/_Internal/PlayerArg+Resolver/PlayerTarget.swift": {
            "lines": 11,
            "tokens": 64,
            "sources": 1,
            "clones": 0,
            "duplicatedLines": 0,
            "duplicatedTokens": 0,
            "percentage": 0,
            "percentageTokens": 0,
            "newDuplicatedLines": 0,
            "newClones": 0
          },
          "./Modules/Sources/Game/_Internal/PlayerArg+Resolver/PlayerSelectReachable.swift": {
            "lines": 14,
            "tokens": 116,
            "sources": 1,
            "clones": 0,
            "duplicatedLines": 0,
            "duplicatedTokens": 0,
            "percentage": 0,
            "percentageTokens": 0,
            "newDuplicatedLines": 0,
            "newClones": 0
          },
          "./Modules/Sources/Game/_Internal/PlayerArg+Resolver/PlayerSelectAt.swift": {
            "lines": 14,
            "tokens": 93,
            "sources": 1,
            "clones": 0,
            "duplicatedLines": 0,
            "duplicatedTokens": 0,
            "percentage": 0,
            "percentageTokens": 0,
            "newDuplicatedLines": 0,
            "newClones": 0
          },
          "./Modules/Sources/Game/_Internal/PlayerArg+Resolver/PlayerSelectAny.swift": {
            "lines": 14,
            "tokens": 94,
            "sources": 1,
            "clones": 0,
            "duplicatedLines": 0,
            "duplicatedTokens": 0,
            "percentage": 0,
            "percentageTokens": 0,
            "newDuplicatedLines": 0,
            "newClones": 0
          },
          "./Modules/Sources/Game/_Internal/PlayerArg+Resolver/PlayerOthers.swift": {
            "lines": 14,
            "tokens": 94,
            "sources": 1,
            "clones": 0,
            "duplicatedLines": 0,
            "duplicatedTokens": 0,
            "percentage": 0,
            "percentageTokens": 0,
            "newDuplicatedLines": 0,
            "newClones": 0
          },
          "./Modules/Sources/Game/_Internal/PlayerArg+Resolver/PlayerNext.swift": {
            "lines": 18,
            "tokens": 142,
            "sources": 1,
            "clones": 0,
            "duplicatedLines": 0,
            "duplicatedTokens": 0,
            "percentage": 0,
            "percentageTokens": 0,
            "newDuplicatedLines": 0,
            "newClones": 0
          },
          "./Modules/Sources/Game/_Internal/PlayerArg+Resolver/PlayerDamaged.swift": {
            "lines": 14,
            "tokens": 103,
            "sources": 1,
            "clones": 0,
            "duplicatedLines": 0,
            "duplicatedTokens": 0,
            "percentage": 0,
            "percentageTokens": 0,
            "newDuplicatedLines": 0,
            "newClones": 0
          },
          "./Modules/Sources/Game/_Internal/PlayerArg+Resolver/PlayerArg+Resolver.swift": {
            "lines": 103,
            "tokens": 805,
            "sources": 1,
            "clones": 0,
            "duplicatedLines": 0,
            "duplicatedTokens": 0,
            "percentage": 0,
            "percentageTokens": 0,
            "newDuplicatedLines": 0,
            "newClones": 0
          },
          "./Modules/Sources/Game/_Internal/PlayerArg+Resolver/PlayerAll.swift": {
            "lines": 13,
            "tokens": 85,
            "sources": 1,
            "clones": 0,
            "duplicatedLines": 0,
            "duplicatedTokens": 0,
            "percentage": 0,
            "percentageTokens": 0,
            "newDuplicatedLines": 0,
            "newClones": 0
          },
          "./Modules/Sources/Game/_Internal/PlayerArg+Resolver/PlayerActor.swift": {
            "lines": 11,
            "tokens": 64,
            "sources": 1,
            "clones": 0,
            "duplicatedLines": 0,
            "duplicatedTokens": 0,
            "percentage": 0,
            "percentageTokens": 0,
            "newDuplicatedLines": 0,
            "newClones": 0
          },
          "./Modules/Sources/Game/_Internal/PlayReq+Matcher/PlayReq+Matcher.swift": {
            "lines": 33,
            "tokens": 233,
            "sources": 1,
            "clones": 0,
            "duplicatedLines": 0,
            "duplicatedTokens": 0,
            "percentage": 0,
            "percentageTokens": 0,
            "newDuplicatedLines": 0,
            "newClones": 0
          },
          "./Modules/Sources/Game/_Internal/PlayReq+Matcher/IsTimesPerTurn.swift": {
            "lines": 20,
            "tokens": 130,
            "sources": 1,
            "clones": 0,
            "duplicatedLines": 0,
            "duplicatedTokens": 0,
            "percentage": 0,
            "percentageTokens": 0,
            "newDuplicatedLines": 0,
            "newClones": 0
          },
          "./Modules/Sources/Game/_Internal/PlayReq+Matcher/IsPlayersAtLeast.swift": {
            "lines": 13,
            "tokens": 69,
            "sources": 1,
            "clones": 0,
            "duplicatedLines": 0,
            "duplicatedTokens": 0,
            "percentage": 0,
            "percentageTokens": 0,
            "newDuplicatedLines": 0,
            "newClones": 0
          },
          "./Modules/Sources/Game/_Internal/PlayReq+Matcher/IsCurrentTurn.swift": {
            "lines": 11,
            "tokens": 64,
            "sources": 1,
            "clones": 0,
            "duplicatedLines": 0,
            "duplicatedTokens": 0,
            "percentage": 0,
            "percentageTokens": 0,
            "newDuplicatedLines": 0,
            "newClones": 0
          },
          "./Modules/Sources/Game/_Internal/NumArg+Resolver/NumPlayers.swift": {
            "lines": 11,
            "tokens": 58,
            "sources": 1,
            "clones": 0,
            "duplicatedLines": 0,
            "duplicatedTokens": 0,
            "percentage": 0,
            "percentageTokens": 0,
            "newDuplicatedLines": 0,
            "newClones": 0
          },
          "./Modules/Sources/Game/_Internal/NumArg+Resolver/NumPlayerAttr.swift": {
            "lines": 14,
            "tokens": 95,
            "sources": 1,
            "clones": 0,
            "duplicatedLines": 0,
            "duplicatedTokens": 0,
            "percentage": 0,
            "percentageTokens": 0,
            "newDuplicatedLines": 0,
            "newClones": 0
          },
          "./Modules/Sources/Game/_Internal/NumArg+Resolver/NumExcessHand.swift": {
            "lines": 19,
            "tokens": 146,
            "sources": 1,
            "clones": 0,
            "duplicatedLines": 0,
            "duplicatedTokens": 0,
            "percentage": 0,
            "percentageTokens": 0,
            "newDuplicatedLines": 0,
            "newClones": 0
          },
          "./Modules/Sources/Game/_Internal/NumArg+Resolver/NumExact.swift": {
            "lines": 13,
            "tokens": 63,
            "sources": 1,
            "clones": 0,
            "duplicatedLines": 0,
            "duplicatedTokens": 0,
            "percentage": 0,
            "percentageTokens": 0,
            "newDuplicatedLines": 0,
            "newClones": 0
          },
          "./Modules/Sources/Game/_Internal/NumArg+Resolver/NumArg+Resolver.swift": {
            "lines": 32,
            "tokens": 228,
            "sources": 1,
            "clones": 0,
            "duplicatedLines": 0,
            "duplicatedTokens": 0,
            "percentage": 0,
            "percentageTokens": 0,
            "newDuplicatedLines": 0,
            "newClones": 0
          },
          "./Modules/Sources/Game/_Internal/Middlewares/GameLoopMiddleware.swift": {
            "lines": 29,
            "tokens": 175,
            "sources": 1,
            "clones": 0,
            "duplicatedLines": 0,
            "duplicatedTokens": 0,
            "percentage": 0,
            "percentageTokens": 0,
            "newDuplicatedLines": 0,
            "newClones": 0
          },
          "./Modules/Sources/Game/_Internal/Middlewares/EventLoggerMiddleware.swift": {
            "lines": 51,
            "tokens": 406,
            "sources": 1,
            "clones": 0,
            "duplicatedLines": 0,
            "duplicatedTokens": 0,
            "percentage": 0,
            "percentageTokens": 0,
            "newDuplicatedLines": 0,
            "newClones": 0
          },
          "./Modules/Sources/Game/_Internal/Middlewares/ActiveCardMiddleware.swift": {
            "lines": 72,
            "tokens": 527,
            "sources": 1,
            "clones": 0,
            "duplicatedLines": 0,
            "duplicatedTokens": 0,
            "percentage": 0,
            "percentageTokens": 0,
            "newDuplicatedLines": 0,
            "newClones": 0
          },
          "./Modules/Sources/Game/_Internal/EventReq+Matcher/OnSetTurn.swift": {
            "lines": 16,
            "tokens": 100,
            "sources": 1,
            "clones": 0,
            "duplicatedLines": 0,
            "duplicatedTokens": 0,
            "percentage": 0,
            "percentageTokens": 0,
            "newDuplicatedLines": 0,
            "newClones": 0
          },
          "./Modules/Sources/Game/_Internal/EventReq+Matcher/OnLooseLastHealth.swift": {
            "lines": 17,
            "tokens": 130,
            "sources": 1,
            "clones": 0,
            "duplicatedLines": 0,
            "duplicatedTokens": 0,
            "percentage": 0,
            "percentageTokens": 0,
            "newDuplicatedLines": 0,
            "newClones": 0
          },
          "./Modules/Sources/Game/_Internal/EventReq+Matcher/OnForceDiscardHandNamed.swift": {
            "lines": 24,
            "tokens": 200,
            "sources": 1,
            "clones": 0,
            "duplicatedLines": 0,
            "duplicatedTokens": 0,
            "percentage": 0,
            "percentageTokens": 0,
            "newDuplicatedLines": 0,
            "newClones": 0
          },
          "./Modules/Sources/Game/_Internal/EventReq+Matcher/OnEliminated.swift": {
            "lines": 16,
            "tokens": 100,
            "sources": 1,
            "clones": 0,
            "duplicatedLines": 0,
            "duplicatedTokens": 0,
            "percentage": 0,
            "percentageTokens": 0,
            "newDuplicatedLines": 0,
            "newClones": 0
          },
          "./Modules/Sources/Game/_Internal/EventReq+Matcher/EventReq+Matcher.swift": {
            "lines": 40,
            "tokens": 273,
            "sources": 1,
            "clones": 0,
            "duplicatedLines": 0,
            "duplicatedTokens": 0,
            "percentage": 0,
            "percentageTokens": 0,
            "newDuplicatedLines": 0,
            "newClones": 0
          },
          "./Modules/Sources/Game/_Internal/Effect+Resolver/EffectTarget.swift": {
            "lines": 16,
            "tokens": 120,
            "sources": 1,
            "clones": 0,
            "duplicatedLines": 0,
            "duplicatedTokens": 0,
            "percentage": 0,
            "percentageTokens": 0,
            "newDuplicatedLines": 0,
            "newClones": 0
          },
          "./Modules/Sources/Game/_Internal/Effect+Resolver/EffectSteal.swift": {
            "lines": 19,
            "tokens": 171,
            "sources": 1,
            "clones": 0,
            "duplicatedLines": 0,
            "duplicatedTokens": 0,
            "percentage": 0,
            "percentageTokens": 0,
            "newDuplicatedLines": 0,
            "newClones": 0
          },
          "./Modules/Sources/Game/_Internal/Effect+Resolver/EffectRepeat.swift": {
            "lines": 17,
            "tokens": 131,
            "sources": 1,
            "clones": 0,
            "duplicatedLines": 0,
            "duplicatedTokens": 0,
            "percentage": 0,
            "percentageTokens": 0,
            "newDuplicatedLines": 0,
            "newClones": 0
          },
          "./Modules/Sources/Game/_Internal/Effect+Resolver/EffectPassInPlay.swift": {
            "lines": 19,
            "tokens": 171,
            "sources": 1,
            "clones": 0,
            "duplicatedLines": 0,
            "duplicatedTokens": 0,
            "percentage": 0,
            "percentageTokens": 0,
            "newDuplicatedLines": 0,
            "newClones": 0
          },
          "./Modules/Sources/Game/_Internal/Effect+Resolver/EffectNone.swift": {
            "lines": 11,
            "tokens": 57,
            "sources": 1,
            "clones": 0,
            "duplicatedLines": 0,
            "duplicatedTokens": 0,
            "percentage": 0,
            "percentageTokens": 0,
            "newDuplicatedLines": 0,
            "newClones": 0
          },
          "./Modules/Sources/Game/_Internal/Effect+Resolver/EffectLuck.swift": {
            "lines": 43,
            "tokens": 354,
            "sources": 1,
            "clones": 0,
            "duplicatedLines": 0,
            "duplicatedTokens": 0,
            "percentage": 0,
            "percentageTokens": 0,
            "newDuplicatedLines": 0,
            "newClones": 0
          },
          "./Modules/Sources/Game/_Internal/Effect+Resolver/EffectGroup.swift": {
            "lines": 13,
            "tokens": 87,
            "sources": 1,
            "clones": 0,
            "duplicatedLines": 0,
            "duplicatedTokens": 0,
            "percentage": 0,
            "percentageTokens": 0,
            "newDuplicatedLines": 0,
            "newClones": 0
          },
          "./Modules/Sources/Game/_Internal/Effect+Resolver/EffectForce.swift": {
            "lines": 40,
            "tokens": 362,
            "sources": 1,
            "clones": 2,
            "duplicatedLines": 24,
            "duplicatedTokens": 247,
            "percentage": 60,
            "percentageTokens": 68.23,
            "newDuplicatedLines": 0,
            "newClones": 0
          },
          "./Modules/Sources/Game/_Internal/Effect+Resolver/EffectEvaluateGameOver.swift": {
            "lines": 25,
            "tokens": 155,
            "sources": 1,
            "clones": 0,
            "duplicatedLines": 0,
            "duplicatedTokens": 0,
            "percentage": 0,
            "percentageTokens": 0,
            "newDuplicatedLines": 0,
            "newClones": 0
          },
          "./Modules/Sources/Game/_Internal/Effect+Resolver/EffectDiscard.swift": {
            "lines": 22,
            "tokens": 184,
            "sources": 1,
            "clones": 0,
            "duplicatedLines": 0,
            "duplicatedTokens": 0,
            "percentage": 0,
            "percentageTokens": 0,
            "newDuplicatedLines": 0,
            "newClones": 0
          },
          "./Modules/Sources/Game/_Internal/Effect+Resolver/EffectChooseCard.swift": {
            "lines": 16,
            "tokens": 132,
            "sources": 1,
            "clones": 0,
            "duplicatedLines": 0,
            "duplicatedTokens": 0,
            "percentage": 0,
            "percentageTokens": 0,
            "newDuplicatedLines": 0,
            "newClones": 0
          },
          "./Modules/Sources/Game/_Internal/Effect+Resolver/EffectChallenge.swift": {
            "lines": 64,
            "tokens": 566,
            "sources": 1,
            "clones": 2,
            "duplicatedLines": 24,
            "duplicatedTokens": 247,
            "percentage": 37.5,
            "percentageTokens": 43.64,
            "newDuplicatedLines": 0,
            "newClones": 0
          },
          "./Modules/Sources/Game/_Internal/Effect+Resolver/EffectBuild.swift": {
            "lines": 14,
            "tokens": 81,
            "sources": 1,
            "clones": 0,
            "duplicatedLines": 0,
            "duplicatedTokens": 0,
            "percentage": 0,
            "percentageTokens": 0,
            "newDuplicatedLines": 0,
            "newClones": 0
          },
          "./Modules/Sources/Game/_Internal/Effect+Resolver/CardEffect+Resolver.swift": {
            "lines": 84,
            "tokens": 756,
            "sources": 1,
            "clones": 0,
            "duplicatedLines": 0,
            "duplicatedTokens": 0,
            "percentage": 0,
            "percentageTokens": 0,
            "newDuplicatedLines": 0,
            "newClones": 0
          },
          "./Modules/Sources/Game/_Internal/CardArg+Resolver/CardSelectHandNamed.swift": {
            "lines": 27,
            "tokens": 161,
            "sources": 1,
            "clones": 1,
            "duplicatedLines": 11,
            "duplicatedTokens": 91,
            "percentage": 40.74,
            "percentageTokens": 56.52,
            "newDuplicatedLines": 0,
            "newClones": 0
          },
          "./Modules/Sources/Game/_Internal/CardArg+Resolver/CardSelectHand.swift": {
            "lines": 23,
            "tokens": 131,
            "sources": 1,
            "clones": 1,
            "duplicatedLines": 11,
            "duplicatedTokens": 91,
            "percentage": 47.83,
            "percentageTokens": 69.47,
            "newDuplicatedLines": 0,
            "newClones": 0
          },
          "./Modules/Sources/Game/_Internal/CardArg+Resolver/CardSelectArena.swift": {
            "lines": 21,
            "tokens": 134,
            "sources": 1,
            "clones": 0,
            "duplicatedLines": 0,
            "duplicatedTokens": 0,
            "percentage": 0,
            "percentageTokens": 0,
            "newDuplicatedLines": 0,
            "newClones": 0
          },
          "./Modules/Sources/Game/_Internal/CardArg+Resolver/CardSelectAny.swift": {
            "lines": 39,
            "tokens": 289,
            "sources": 1,
            "clones": 0,
            "duplicatedLines": 0,
            "duplicatedTokens": 0,
            "percentage": 0,
            "percentageTokens": 0,
            "newDuplicatedLines": 0,
            "newClones": 0
          },
          "./Modules/Sources/Game/_Internal/CardArg+Resolver/CardPlayed.swift": {
            "lines": 11,
            "tokens": 77,
            "sources": 1,
            "clones": 0,
            "duplicatedLines": 0,
            "duplicatedTokens": 0,
            "percentage": 0,
            "percentageTokens": 0,
            "newDuplicatedLines": 0,
            "newClones": 0
          },
          "./Modules/Sources/Game/_Internal/CardArg+Resolver/CardArg+Resolver.swift": {
            "lines": 106,
            "tokens": 708,
            "sources": 1,
            "clones": 0,
            "duplicatedLines": 0,
            "duplicatedTokens": 0,
            "percentage": 0,
            "percentageTokens": 0,
            "newDuplicatedLines": 0,
            "newClones": 0
          },
          "./Modules/Sources/Game/_Internal/CardArg+Resolver/CardAll.swift": {
            "lines": 13,
            "tokens": 112,
            "sources": 1,
            "clones": 0,
            "duplicatedLines": 0,
            "duplicatedTokens": 0,
            "percentage": 0,
            "percentageTokens": 0,
            "newDuplicatedLines": 0,
            "newClones": 0
          },
          "./Modules/Sources/Game/_Internal/Action+Reducer/GameAction+Validate.swift": {
            "lines": 56,
            "tokens": 437,
            "sources": 1,
            "clones": 0,
            "duplicatedLines": 0,
            "duplicatedTokens": 0,
            "percentage": 0,
            "percentageTokens": 0,
            "newDuplicatedLines": 0,
            "newClones": 0
          },
          "./Modules/Sources/Game/_Internal/Action+Reducer/GameAction+Reducer.swift": {
            "lines": 71,
            "tokens": 807,
            "sources": 1,
            "clones": 0,
            "duplicatedLines": 0,
            "duplicatedTokens": 0,
            "percentage": 0,
            "percentageTokens": 0,
            "newDuplicatedLines": 0,
            "newClones": 0
          },
          "./Modules/Sources/Game/_Internal/Action+Reducer/ActionSteal.swift": {
            "lines": 18,
            "tokens": 130,
            "sources": 1,
            "clones": 0,
            "duplicatedLines": 0,
            "duplicatedTokens": 0,
            "percentage": 0,
            "percentageTokens": 0,
            "newDuplicatedLines": 0,
            "newClones": 0
          },
          "./Modules/Sources/Game/_Internal/Action+Reducer/ActionSetTurn.swift": {
            "lines": 16,
            "tokens": 88,
            "sources": 1,
            "clones": 0,
            "duplicatedLines": 0,
            "duplicatedTokens": 0,
            "percentage": 0,
            "percentageTokens": 0,
            "newDuplicatedLines": 0,
            "newClones": 0
          },
          "./Modules/Sources/Game/_Internal/Action+Reducer/ActionSetGameOver.swift": {
            "lines": 15,
            "tokens": 83,
            "sources": 1,
            "clones": 0,
            "duplicatedLines": 0,
            "duplicatedTokens": 0,
            "percentage": 0,
            "percentageTokens": 0,
            "newDuplicatedLines": 0,
            "newClones": 0
          },
          "./Modules/Sources/Game/_Internal/Action+Reducer/ActionResolve.swift": {
            "lines": 17,
            "tokens": 121,
            "sources": 1,
            "clones": 0,
            "duplicatedLines": 0,
            "duplicatedTokens": 0,
            "percentage": 0,
            "percentageTokens": 0,
            "newDuplicatedLines": 0,
            "newClones": 0
          },
          "./Modules/Sources/Game/_Internal/Action+Reducer/ActionPlayImmediate.swift": {
            "lines": 48,
            "tokens": 443,
            "sources": 1,
            "clones": 2,
            "duplicatedLines": 15,
            "duplicatedTokens": 204,
            "percentage": 31.25,
            "percentageTokens": 46.05,
            "newDuplicatedLines": 0,
            "newClones": 0
          },
          "./Modules/Sources/Game/_Internal/Action+Reducer/ActionPlayHandicap.swift": {
            "lines": 31,
            "tokens": 278,
            "sources": 1,
            "clones": 2,
            "duplicatedLines": 15,
            "duplicatedTokens": 169,
            "percentage": 48.39,
            "percentageTokens": 60.79,
            "newDuplicatedLines": 0,
            "newClones": 0
          },
          "./Modules/Sources/Game/_Internal/Action+Reducer/ActionPlayEquipment.swift": {
            "lines": 29,
            "tokens": 255,
            "sources": 1,
            "clones": 2,
            "duplicatedLines": 15,
            "duplicatedTokens": 169,
            "percentage": 51.72,
            "percentageTokens": 66.27,
            "newDuplicatedLines": 0,
            "newClones": 0
          },
          "./Modules/Sources/Game/_Internal/Action+Reducer/ActionPlayAbility.swift": {
            "lines": 29,
            "tokens": 251,
            "sources": 1,
            "clones": 1,
            "duplicatedLines": 7,
            "duplicatedTokens": 99,
            "percentage": 24.14,
            "percentageTokens": 39.44,
            "newDuplicatedLines": 0,
            "newClones": 0
          },
          "./Modules/Sources/Game/_Internal/Action+Reducer/ActionPlay.swift": {
            "lines": 72,
            "tokens": 666,
            "sources": 1,
            "clones": 1,
            "duplicatedLines": 8,
            "duplicatedTokens": 105,
            "percentage": 11.11,
            "percentageTokens": 15.77,
            "newDuplicatedLines": 0,
            "newClones": 0
          },
          "./Modules/Sources/Game/_Internal/Action+Reducer/ActionPassInPlay.swift": {
            "lines": 18,
            "tokens": 131,
            "sources": 1,
            "clones": 0,
            "duplicatedLines": 0,
            "duplicatedTokens": 0,
            "percentage": 0,
            "percentageTokens": 0,
            "newDuplicatedLines": 0,
            "newClones": 0
          },
          "./Modules/Sources/Game/_Internal/Action+Reducer/ActionLuck.swift": {
            "lines": 14,
            "tokens": 84,
            "sources": 1,
            "clones": 0,
            "duplicatedLines": 0,
            "duplicatedTokens": 0,
            "percentage": 0,
            "percentageTokens": 0,
            "newDuplicatedLines": 0,
            "newClones": 0
          },
          "./Modules/Sources/Game/_Internal/Action+Reducer/ActionHeal.swift": {
            "lines": 16,
            "tokens": 99,
            "sources": 1,
            "clones": 0,
            "duplicatedLines": 0,
            "duplicatedTokens": 0,
            "percentage": 0,
            "percentageTokens": 0,
            "newDuplicatedLines": 0,
            "newClones": 0
          },
          "./Modules/Sources/Game/_Internal/Action+Reducer/ActionGroup.swift": {
            "lines": 15,
            "tokens": 89,
            "sources": 1,
            "clones": 0,
            "duplicatedLines": 0,
            "duplicatedTokens": 0,
            "percentage": 0,
            "percentageTokens": 0,
            "newDuplicatedLines": 0,
            "newClones": 0
          },
          "./Modules/Sources/Game/_Internal/Action+Reducer/ActionEliminate.swift": {
            "lines": 26,
            "tokens": 198,
            "sources": 1,
            "clones": 0,
            "duplicatedLines": 0,
            "duplicatedTokens": 0,
            "percentage": 0,
            "percentageTokens": 0,
            "newDuplicatedLines": 0,
            "newClones": 0
          },
          "./Modules/Sources/Game/_Internal/Action+Reducer/ActionDraw.swift": {
            "lines": 16,
            "tokens": 106,
            "sources": 1,
            "clones": 0,
            "duplicatedLines": 0,
            "duplicatedTokens": 0,
            "percentage": 0,
            "percentageTokens": 0,
            "newDuplicatedLines": 0,
            "newClones": 0
          },
          "./Modules/Sources/Game/_Internal/Action+Reducer/ActionDiscover.swift": {
            "lines": 17,
            "tokens": 113,
            "sources": 1,
            "clones": 0,
            "duplicatedLines": 0,
            "duplicatedTokens": 0,
            "percentage": 0,
            "percentageTokens": 0,
            "newDuplicatedLines": 0,
            "newClones": 0
          },
          "./Modules/Sources/Game/_Internal/Action+Reducer/ActionDiscard.swift": {
            "lines": 17,
            "tokens": 109,
            "sources": 1,
            "clones": 0,
            "duplicatedLines": 0,
            "duplicatedTokens": 0,
            "percentage": 0,
            "percentageTokens": 0,
            "newDuplicatedLines": 0,
            "newClones": 0
          },
          "./Modules/Sources/Game/_Internal/Action+Reducer/ActionDamage.swift": {
            "lines": 16,
            "tokens": 97,
            "sources": 1,
            "clones": 0,
            "duplicatedLines": 0,
            "duplicatedTokens": 0,
            "percentage": 0,
            "percentageTokens": 0,
            "newDuplicatedLines": 0,
            "newClones": 0
          },
          "./Modules/Sources/Game/_Internal/Action+Reducer/ActionChooseOne.swift": {
            "lines": 16,
            "tokens": 102,
            "sources": 1,
            "clones": 0,
            "duplicatedLines": 0,
            "duplicatedTokens": 0,
            "percentage": 0,
            "percentageTokens": 0,
            "newDuplicatedLines": 0,
            "newClones": 0
          },
          "./Modules/Sources/Game/_Internal/Action+Reducer/ActionChooseCard.swift": {
            "lines": 20,
            "tokens": 142,
            "sources": 1,
            "clones": 0,
            "duplicatedLines": 0,
            "duplicatedTokens": 0,
            "percentage": 0,
            "percentageTokens": 0,
            "newDuplicatedLines": 0,
            "newClones": 0
          },
          "./Modules/Sources/Game/_Internal/Action+Reducer/ActionCancel.swift": {
            "lines": 36,
            "tokens": 249,
            "sources": 1,
            "clones": 0,
            "duplicatedLines": 0,
            "duplicatedTokens": 0,
            "percentage": 0,
            "percentageTokens": 0,
            "newDuplicatedLines": 0,
            "newClones": 0
          },
          "./Modules/Sources/Game/_Internal/Action+Reducer/ActionActivateCard.swift": {
            "lines": 16,
            "tokens": 99,
            "sources": 1,
            "clones": 0,
            "duplicatedLines": 0,
            "duplicatedTokens": 0,
            "percentage": 0,
            "percentageTokens": 0,
            "newDuplicatedLines": 0,
            "newClones": 0
          },
          "./Modules/Sources/Game/Public/Setup/Setup.swift": {
            "lines": 48,
            "tokens": 459,
            "sources": 1,
            "clones": 0,
            "duplicatedLines": 0,
            "duplicatedTokens": 0,
            "percentage": 0,
            "percentageTokens": 0,
            "newDuplicatedLines": 0,
            "newClones": 0
          },
          "./Modules/Sources/Game/Public/Models/PlayerArg.swift": {
            "lines": 39,
            "tokens": 125,
            "sources": 1,
            "clones": 0,
            "duplicatedLines": 0,
            "duplicatedTokens": 0,
            "percentage": 0,
            "percentageTokens": 0,
            "newDuplicatedLines": 0,
            "newClones": 0
          },
          "./Modules/Sources/Game/Public/Models/Player.swift": {
            "lines": 29,
            "tokens": 158,
            "sources": 1,
            "clones": 0,
            "duplicatedLines": 0,
            "duplicatedTokens": 0,
            "percentage": 0,
            "percentageTokens": 0,
            "newDuplicatedLines": 0,
            "newClones": 0
          },
          "./Modules/Sources/Game/Public/Models/PlayReq.swift": {
            "lines": 18,
            "tokens": 62,
            "sources": 1,
            "clones": 0,
            "duplicatedLines": 0,
            "duplicatedTokens": 0,
            "percentage": 0,
            "percentageTokens": 0,
            "newDuplicatedLines": 0,
            "newClones": 0
          },
          "./Modules/Sources/Game/Public/Models/NumArg.swift": {
            "lines": 21,
            "tokens": 72,
            "sources": 1,
            "clones": 0,
            "duplicatedLines": 0,
            "duplicatedTokens": 0,
            "percentage": 0,
            "percentageTokens": 0,
            "newDuplicatedLines": 0,
            "newClones": 0
          },
          "./Modules/Sources/Game/Public/Models/GameState.swift": {
            "lines": 67,
            "tokens": 417,
            "sources": 1,
            "clones": 0,
            "duplicatedLines": 0,
            "duplicatedTokens": 0,
            "percentage": 0,
            "percentageTokens": 0,
            "newDuplicatedLines": 0,
            "newClones": 0
          },
          "./Modules/Sources/Game/Public/Models/GameOver.swift": {
            "lines": 14,
            "tokens": 64,
            "sources": 1,
            "clones": 0,
            "duplicatedLines": 0,
            "duplicatedTokens": 0,
            "percentage": 0,
            "percentageTokens": 0,
            "newDuplicatedLines": 0,
            "newClones": 0
          },
          "./Modules/Sources/Game/Public/Models/GameError.swift": {
            "lines": 43,
            "tokens": 151,
            "sources": 1,
            "clones": 0,
            "duplicatedLines": 0,
            "duplicatedTokens": 0,
            "percentage": 0,
            "percentageTokens": 0,
            "newDuplicatedLines": 0,
            "newClones": 0
          },
          "./Modules/Sources/Game/Public/Models/GameElement.swift": {
            "lines": 16,
            "tokens": 64,
            "sources": 1,
            "clones": 0,
            "duplicatedLines": 0,
            "duplicatedTokens": 0,
            "percentage": 0,
            "percentageTokens": 0,
            "newDuplicatedLines": 0,
            "newClones": 0
          },
          "./Modules/Sources/Game/Public/Models/GameAction.swift": {
            "lines": 93,
            "tokens": 510,
            "sources": 1,
            "clones": 0,
            "duplicatedLines": 0,
            "duplicatedTokens": 0,
            "percentage": 0,
            "percentageTokens": 0,
            "newDuplicatedLines": 0,
            "newClones": 0
          },
          "./Modules/Sources/Game/Public/Models/Figure.swift": {
            "lines": 18,
            "tokens": 118,
            "sources": 1,
            "clones": 0,
            "duplicatedLines": 0,
            "duplicatedTokens": 0,
            "percentage": 0,
            "percentageTokens": 0,
            "newDuplicatedLines": 0,
            "newClones": 0
          },
          "./Modules/Sources/Game/Public/Models/EventReq.swift": {
            "lines": 24,
            "tokens": 78,
            "sources": 1,
            "clones": 0,
            "duplicatedLines": 0,
            "duplicatedTokens": 0,
            "percentage": 0,
            "percentageTokens": 0,
            "newDuplicatedLines": 0,
            "newClones": 0
          },
          "./Modules/Sources/Game/Public/Models/EffectContext.swift": {
            "lines": 20,
            "tokens": 78,
            "sources": 1,
            "clones": 0,
            "duplicatedLines": 0,
            "duplicatedTokens": 0,
            "percentage": 0,
            "percentageTokens": 0,
            "newDuplicatedLines": 0,
            "newClones": 0
          },
          "./Modules/Sources/Game/Public/Models/ChooseOne.swift": {
            "lines": 26,
            "tokens": 141,
            "sources": 1,
            "clones": 0,
            "duplicatedLines": 0,
            "duplicatedTokens": 0,
            "percentage": 0,
            "percentageTokens": 0,
            "newDuplicatedLines": 0,
            "newClones": 0
          },
          "./Modules/Sources/Game/Public/Models/CardStack.swift": {
            "lines": 18,
            "tokens": 95,
            "sources": 1,
            "clones": 0,
            "duplicatedLines": 0,
            "duplicatedTokens": 0,
            "percentage": 0,
            "percentageTokens": 0,
            "newDuplicatedLines": 0,
            "newClones": 0
          },
          "./Modules/Sources/Game/Public/Models/CardLocation.swift": {
            "lines": 18,
            "tokens": 87,
            "sources": 1,
            "clones": 0,
            "duplicatedLines": 0,
            "duplicatedTokens": 0,
            "percentage": 0,
            "percentageTokens": 0,
            "newDuplicatedLines": 0,
            "newClones": 0
          },
          "./Modules/Sources/Game/Public/Models/CardEffect.swift": {
            "lines": 80,
            "tokens": 383,
            "sources": 1,
            "clones": 0,
            "duplicatedLines": 0,
            "duplicatedTokens": 0,
            "percentage": 0,
            "percentageTokens": 0,
            "newDuplicatedLines": 0,
            "newClones": 0
          },
          "./Modules/Sources/Game/Public/Models/CardArg.swift": {
            "lines": 30,
            "tokens": 99,
            "sources": 1,
            "clones": 0,
            "duplicatedLines": 0,
            "duplicatedTokens": 0,
            "percentage": 0,
            "percentageTokens": 0,
            "newDuplicatedLines": 0,
            "newClones": 0
          },
          "./Modules/Sources/Game/Public/Models/Card.swift": {
            "lines": 28,
            "tokens": 119,
            "sources": 1,
            "clones": 0,
            "duplicatedLines": 0,
            "duplicatedTokens": 0,
            "percentage": 0,
            "percentageTokens": 0,
            "newDuplicatedLines": 0,
            "newClones": 0
          },
          "./Modules/Sources/Game/Public/Models/CancelArg.swift": {
            "lines": 15,
            "tokens": 50,
            "sources": 1,
            "clones": 0,
            "duplicatedLines": 0,
            "duplicatedTokens": 0,
            "percentage": 0,
            "percentageTokens": 0,
            "newDuplicatedLines": 0,
            "newClones": 0
          },
          "./Modules/Sources/Game/Public/Models/AttributeKey.swift": {
            "lines": 39,
            "tokens": 132,
            "sources": 1,
            "clones": 0,
            "duplicatedLines": 0,
            "duplicatedTokens": 0,
            "percentage": 0,
            "percentageTokens": 0,
            "newDuplicatedLines": 0,
            "newClones": 0
          },
          "./Modules/Sources/Game/Public/Models/ActiveCards.swift": {
            "lines": 15,
            "tokens": 92,
            "sources": 1,
            "clones": 0,
            "duplicatedLines": 0,
            "duplicatedTokens": 0,
            "percentage": 0,
            "percentageTokens": 0,
            "newDuplicatedLines": 0,
            "newClones": 0
          },
          "./Modules/Sources/UI/Utils/CircleImage.swift": {
            "lines": 25,
            "tokens": 147,
            "sources": 1,
            "clones": 0,
            "duplicatedLines": 0,
            "duplicatedTokens": 0,
            "percentage": 0,
            "percentageTokens": 0,
            "newDuplicatedLines": 0,
            "newClones": 0
          },
          "./Modules/Sources/UI/Splash/SplashView.swift": {
            "lines": 41,
            "tokens": 255,
            "sources": 1,
            "clones": 0,
            "duplicatedLines": 0,
            "duplicatedTokens": 0,
            "percentage": 0,
            "percentageTokens": 0,
            "newDuplicatedLines": 0,
            "newClones": 0
          },
          "./Modules/Sources/UI/Home/HomeView.swift": {
            "lines": 43,
            "tokens": 245,
            "sources": 1,
            "clones": 0,
            "duplicatedLines": 0,
            "duplicatedTokens": 0,
            "percentage": 0,
            "percentageTokens": 0,
            "newDuplicatedLines": 0,
            "newClones": 0
          },
          "./Modules/Sources/UI/Home/Home.swift": {
            "lines": 21,
            "tokens": 105,
            "sources": 1,
            "clones": 0,
            "duplicatedLines": 0,
            "duplicatedTokens": 0,
            "percentage": 0,
            "percentageTokens": 0,
            "newDuplicatedLines": 0,
            "newClones": 0
          },
          "./Modules/Sources/UI/GamePlay/PlayerView.swift": {
            "lines": 40,
            "tokens": 233,
            "sources": 1,
            "clones": 0,
            "duplicatedLines": 0,
            "duplicatedTokens": 0,
            "percentage": 0,
            "percentageTokens": 0,
            "newDuplicatedLines": 0,
            "newClones": 0
          },
          "./Modules/Sources/UI/GamePlay/GamePlayView.swift": {
            "lines": 82,
            "tokens": 557,
            "sources": 1,
            "clones": 0,
            "duplicatedLines": 0,
            "duplicatedTokens": 0,
            "percentage": 0,
            "percentageTokens": 0,
            "newDuplicatedLines": 0,
            "newClones": 0
          },
          "./Modules/Sources/UI/GamePlay/GamePlay.swift": {
            "lines": 24,
            "tokens": 141,
            "sources": 1,
            "clones": 0,
            "duplicatedLines": 0,
            "duplicatedTokens": 0,
            "percentage": 0,
            "percentageTokens": 0,
            "newDuplicatedLines": 0,
            "newClones": 0
          },
          "./Modules/Sources/UI/App/AppView.swift": {
            "lines": 46,
            "tokens": 256,
            "sources": 1,
            "clones": 0,
            "duplicatedLines": 0,
            "duplicatedTokens": 0,
            "percentage": 0,
            "percentageTokens": 0,
            "newDuplicatedLines": 0,
            "newClones": 0
          },
          "./Modules/Sources/UI/App/AppReducer.swift": {
            "lines": 85,
            "tokens": 628,
            "sources": 1,
            "clones": 0,
            "duplicatedLines": 0,
            "duplicatedTokens": 0,
            "percentage": 0,
            "percentageTokens": 0,
            "newDuplicatedLines": 0,
            "newClones": 0
          },
          "./Modules/Sources/Game/Public/GameStore.swift": {
            "lines": 18,
            "tokens": 88,
            "sources": 1,
            "clones": 0,
            "duplicatedLines": 0,
            "duplicatedTokens": 0,
            "percentage": 0,
            "percentageTokens": 0,
            "newDuplicatedLines": 0,
            "newClones": 0
          },
          "./Modules/Sources/Game/Public/GameReducer.swift": {
            "lines": 105,
            "tokens": 954,
            "sources": 1,
            "clones": 0,
            "duplicatedLines": 0,
            "duplicatedTokens": 0,
            "percentage": 0,
            "percentageTokens": 0,
            "newDuplicatedLines": 0,
            "newClones": 0
          },
          "./Modules/Sources/Redux/Store.swift": {
            "lines": 44,
            "tokens": 418,
            "sources": 1,
            "clones": 0,
            "duplicatedLines": 0,
            "duplicatedTokens": 0,
            "percentage": 0,
            "percentageTokens": 0,
            "newDuplicatedLines": 0,
            "newClones": 0
          },
          "./Modules/Sources/Redux/ReducerProtocol.swift": {
            "lines": 31,
            "tokens": 138,
            "sources": 1,
            "clones": 0,
            "duplicatedLines": 0,
            "duplicatedTokens": 0,
            "percentage": 0,
            "percentageTokens": 0,
            "newDuplicatedLines": 0,
            "newClones": 0
          },
          "./Modules/Sources/Inventory/String+CardName.swift": {
            "lines": 68,
            "tokens": 568,
            "sources": 1,
            "clones": 0,
            "duplicatedLines": 0,
            "duplicatedTokens": 0,
            "percentage": 0,
            "percentageTokens": 0,
            "newDuplicatedLines": 0,
            "newClones": 0
          },
          "./Modules/Sources/Inventory/Inventory.swift": {
            "lines": 46,
            "tokens": 489,
            "sources": 1,
            "clones": 0,
            "duplicatedLines": 0,
            "duplicatedTokens": 0,
            "percentage": 0,
            "percentageTokens": 0,
            "newDuplicatedLines": 0,
            "newClones": 0
          },
          "./Modules/Sources/Inventory/CardSets.swift": {
            "lines": 33,
            "tokens": 375,
            "sources": 1,
            "clones": 0,
            "duplicatedLines": 0,
            "duplicatedTokens": 0,
            "percentage": 0,
            "percentageTokens": 0,
            "newDuplicatedLines": 0,
            "newClones": 0
          },
          "./Modules/Sources/Inventory/CardList.swift": {
            "lines": 204,
            "tokens": 1565,
            "sources": 1,
            "clones": 0,
            "duplicatedLines": 0,
            "duplicatedTokens": 0,
            "percentage": 0,
            "percentageTokens": 0,
            "newDuplicatedLines": 0,
            "newClones": 0
          }
        },
        "total": {
          "lines": 4302,
          "tokens": 30063,
          "sources": 143,
          "clones": 8,
          "duplicatedLines": 76,
          "duplicatedTokens": 810,
          "percentage": 1.77,
          "percentageTokens": 2.69,
          "newDuplicatedLines": 0,
          "newClones": 0
        }
      }
    },
    "total": {
      "lines": 5202,
      "tokens": 35055,
      "sources": 191,
      "clones": 8,
      "duplicatedLines": 76,
      "duplicatedTokens": 810,
      "percentage": 1.46,
      "percentageTokens": 2.31,
      "newDuplicatedLines": 0,
      "newClones": 0
    }
  },
  "duplicates": [
    {
      "format": "swift",
      "lines": 12,
      "fragment": "}\n    }\n\n    func attribute(_ key: AttributeKey, _ value: Int) -> Self {\n        copy { $0.attributes[key] = value }\n    }\n\n    func ability(_ value: String) -> Self {\n        copy { $0.abilities.append(value) }\n    }\n\n    func",
      "tokens": 0,
      "firstFile": {
        "name": "Modules/Sources/Game/Public/DSL/Modifiers/GameState+Modifiers.swift",
        "start": 31,
        "end": 42,
        "startLoc": {
          "line": 31,
          "column": 2,
          "position": 313
        },
        "endLoc": {
          "line": 42,
          "column": 5,
          "position": 412
        }
      },
      "secondFile": {
        "name": "Modules/Sources/Game/Public/DSL/Modifiers/Player+Modifiers.swift",
        "start": 24,
        "end": 34,
        "startLoc": {
          "line": 24,
          "column": 2,
          "position": 185
        },
        "endLoc": {
          "line": 34,
          "column": 2,
          "position": 283
        }
      }
    },
    {
      "format": "swift",
      "lines": 11,
      "fragment": "do {\n            let children = try effect.resolve(state: state, ctx: ctx)\n            \n            guard children.count == 1 else {\n                fatalError(\"unexpected\")\n            }\n            \n            let action = children[0]\n            switch action {\n            case let .resolve(childEffect, childCtx):\n                return [.resolve(.challenge",
      "tokens": 0,
      "firstFile": {
        "name": "Modules/Sources/Game/_Internal/Effect+Resolver/EffectChallenge.swift",
        "start": 25,
        "end": 35,
        "startLoc": {
          "line": 25,
          "column": 9,
          "position": 183
        },
        "endLoc": {
          "line": 35,
          "column": 10,
          "position": 282
        }
      },
      "secondFile": {
        "name": "Modules/Sources/Game/_Internal/Effect+Resolver/EffectForce.swift",
        "start": 13,
        "end": 23,
        "startLoc": {
          "line": 13,
          "column": 9,
          "position": 69
        },
        "endLoc": {
          "line": 23,
          "column": 6,
          "position": 168
        }
      }
    },
    {
      "format": "swift",
      "lines": 15,
      "fragment": "options[.pass] = .resolve(otherwise, ctx: ctx)\n                let chooseOne = try GameAction.validChooseOne(chooser: chooser, options: options, state: state)\n                return [chooseOne]\n                \n            default:\n                fatalError(\"unexpected\")\n            }\n        } catch {\n            let chooseOne = try GameAction.validChooseOne(chooser: ctx.get(.target),\n                                                          options: [.pass: .resolve(otherwise, ctx: ctx)],\n                                                          state: state)\n            return [chooseOne]\n        }\n    }\n}",
      "tokens": 0,
      "firstFile": {
        "name": "Modules/Sources/Game/_Internal/Effect+Resolver/EffectChallenge.swift",
        "start": 51,
        "end": 65,
        "startLoc": {
          "line": 51,
          "column": 17,
          "position": 418
        },
        "endLoc": {
          "line": 65,
          "column": 2,
          "position": 566
        }
      },
      "secondFile": {
        "name": "Modules/Sources/Game/_Internal/Effect+Resolver/EffectForce.swift",
        "start": 27,
        "end": 41,
        "startLoc": {
          "line": 27,
          "column": 17,
          "position": 214
        },
        "endLoc": {
          "line": 41,
          "column": 2,
          "position": 362
        }
      }
    },
    {
      "format": "swift",
      "lines": 12,
      "fragment": "func resolve(\n        state: GameState,\n        ctx: EffectContext,\n        chooser: String,\n        owner: String?\n    ) -> CardArgOutput {\n        guard let owner else {\n            fatalError(\"unexpected\")\n        }\n\n        let playerObj = state.player(owner)\n        let options = playerObj.hand.cards.toCardOptions",
      "tokens": 0,
      "firstFile": {
        "name": "Modules/Sources/Game/_Internal/CardArg+Resolver/CardSelectHand.swift",
        "start": 9,
        "end": 20,
        "startLoc": {
          "line": 9,
          "column": 5,
          "position": 23
        },
        "endLoc": {
          "line": 20,
          "column": 14,
          "position": 114
        }
      },
      "secondFile": {
        "name": "Modules/Sources/Game/_Internal/CardArg+Resolver/CardSelectHandNamed.swift",
        "start": 11,
        "end": 23,
        "startLoc": {
          "line": 11,
          "column": 5,
          "position": 32
        },
        "endLoc": {
          "line": 23,
          "column": 7,
          "position": 125
        }
      }
    },
    {
      "format": "swift",
      "lines": 11,
      "fragment": ": String\n\n    func reduce(state: GameState) throws -> GameState {\n        var state = state\n        let actorObj = state.player(actor)\n        guard actorObj.hand.contains(card) else {\n            throw GameError.cardNotFound(card)\n        }\n\n        let cardName = card.extractName()\n        guard",
      "tokens": 0,
      "firstFile": {
        "name": "Modules/Sources/Game/_Internal/Action+Reducer/ActionPlayEquipment.swift",
        "start": 10,
        "end": 20,
        "startLoc": {
          "line": 10,
          "column": 5,
          "position": 34
        },
        "endLoc": {
          "line": 20,
          "column": 6,
          "position": 126
        }
      },
      "secondFile": {
        "name": "Modules/Sources/Game/_Internal/Action+Reducer/ActionPlayHandicap.swift",
        "start": 11,
        "end": 21,
        "startLoc": {
          "line": 11,
          "column": 7,
          "position": 42
        },
        "endLoc": {
          "line": 21,
          "column": 4,
          "position": 134
        }
      }
    },
    {
      "format": "swift",
      "lines": 6,
      "fragment": ".inPlay.cards.allSatisfy({ $0.extractName() != cardName }) else {\n            throw GameError.cardAlreadyInPlay(cardName)\n        }\n\n        try state[keyPath: \\GameState.players[actor]]?.hand.remove(card)\n        state[keyPath: \\GameState.players[actor",
      "tokens": 0,
      "firstFile": {
        "name": "Modules/Sources/Game/_Internal/Action+Reducer/ActionPlayEquipment.swift",
        "start": 20,
        "end": 25,
        "startLoc": {
          "line": 20,
          "column": 9,
          "position": 129
        },
        "endLoc": {
          "line": 25,
          "column": 6,
          "position": 206
        }
      },
      "secondFile": {
        "name": "Modules/Sources/Game/_Internal/Action+Reducer/ActionPlayHandicap.swift",
        "start": 22,
        "end": 27,
        "startLoc": {
          "line": 22,
          "column": 10,
          "position": 151
        },
        "endLoc": {
          "line": 27,
          "column": 7,
          "position": 229
        }
      }
    },
    {
      "format": "swift",
      "lines": 8,
      "fragment": "func reduce(state: GameState) throws -> GameState {\n        let cardName = card.extractName()\n        guard let cardObj = state.cardRef[cardName],\n              let playAction = cardObj.actions.first(where: { $0.eventReq == .onPlay }) else {\n            throw GameError.cardNotPlayable(card)\n        }\n\n        let",
      "tokens": 0,
      "firstFile": {
        "name": "Modules/Sources/Game/_Internal/Action+Reducer/ActionPlayAbility.swift",
        "start": 12,
        "end": 19,
        "startLoc": {
          "line": 12,
          "column": 5,
          "position": 40
        },
        "endLoc": {
          "line": 19,
          "column": 4,
          "position": 139
        }
      },
      "secondFile": {
        "name": "Modules/Sources/Game/_Internal/Action+Reducer/ActionPlayImmediate.swift",
        "start": 13,
        "end": 20,
        "startLoc": {
          "line": 13,
          "column": 5,
          "position": 49
        },
        "endLoc": {
          "line": 20,
          "column": 4,
          "position": 148
        }
      }
    },
    {
      "format": "swift",
      "lines": 9,
      "fragment": "let cardName = card.extractName()\n        guard let cardObj = state.cardRef[cardName],\n              let playAction = cardObj.actions.first(where: { $0.eventReq == .onPlay }) else {\n            throw GameError.cardNotPlayable(card)\n        }\n\n        let ctx: EffectContext = [.actor: actor, .card: card]\n\n        // verify requirements",
      "tokens": 0,
      "firstFile": {
        "name": "Modules/Sources/Game/_Internal/Action+Reducer/ActionPlay.swift",
        "start": 15,
        "end": 23,
        "startLoc": {
          "line": 15,
          "column": 9,
          "position": 66
        },
        "endLoc": {
          "line": 23,
          "column": 23,
          "position": 171
        }
      },
      "secondFile": {
        "name": "Modules/Sources/Game/_Internal/Action+Reducer/ActionPlayImmediate.swift",
        "start": 14,
        "end": 21,
        "startLoc": {
          "line": 14,
          "column": 9,
          "position": 69
        },
        "endLoc": {
          "line": 21,
          "column": 4,
          "position": 165
        }
      }
    }
  ]
}